{"candidaturas":[{"candidatos_principales":{"CON":{"descripcion":"DANIEL ANGEL ARAVENA","dni":"23346678","id_candidatura":"151.32"},"INT":{"descripcion":"NORMA ESTHER SEPULVEDA","dni":"28002795","id_candidatura":"151.31"}},"clase":"Lista","color":null,"descripcion_lista":"MOVIMIENTO POPULAR NEUQUINO","id_candidatura":"151","incluir_en_calculo_porcentaje":true,"nombre_corto":"MPN","nro_lista":"151"},{"candidatos_principales":{"CON":{"descripcion":"DANIEL ANGEL ARAVENA","dni":"23346678","id_candidatura":"166.106"},"INT":{"descripcion":"NORMA ESTHER SEPULVEDA","dni":"28002795","id_candidatura":"166.105"}},"clase":"Lista","color":null,"descripcion_lista":"UNION DE LOS NEUQUINOS - UNE","id_candidatura":"166","incluir_en_calculo_porcentaje":true,"nombre_corto":"UN","nro_lista":"166"},{"candidatos_principales":{"CON":{"descripcion":"RICARDO GABRIEL MU\u00d1OZ","dni":"16979944","id_candidatura":"194.61"},"INT":{"descripcion":"JOSE ALBERTO QUINTERO MARCO","dni":"22473462","id_candidatura":"194.60"}},"clase":"Lista","color":null,"descripcion_lista":"ENCUENTRO REPUBLICANO FEDERAL","id_candidatura":"194","incluir_en_calculo_porcentaje":true,"nombre_corto":"ERF","nro_lista":"194"},{"candidatos_principales":{"CON":{"descripcion":"LUCIANO JUAN DOMINGO JOUBERT","dni":"29045889","id_candidatura":"50.76"},"INT":{"descripcion":"JOSE ALBERTO QUINTERO MARCO","dni":"22473462","id_candidatura":"50.75"}},"clase":"Lista","color":null,"descripcion_lista":"PARTIDO SOCIALISTA","id_candidatura":"50","incluir_en_calculo_porcentaje":true,"nombre_corto":"PS","nro_lista":"50"},{"candidatos_principales":{"CON":{"descripcion":"JUAN JOSE MALDONADO","dni":"16831451","id_candidatura":"67.91"},"INT":{"descripcion":"CESAR AURELIO GODOY","dni":"31530215","id_candidatura":"67.90"}},"clase":"Lista","color":null,"descripcion_lista":"KOLINA","id_candidatura":"67","incluir_en_calculo_porcentaje":true,"nombre_corto":"KL","nro_lista":"67"},{"candidatos_principales":{"CON":{"descripcion":"WALTER JOSE ZOZAYA","dni":"22910330","id_candidatura":"72.17"},"INT":{"descripcion":"CESAR AURELIO GODOY","dni":"31530215","id_candidatura":"72.16"}},"clase":"Lista","color":null,"descripcion_lista":"INSTRUMENTO ELECTORAL POR LA UNIDAD POPULAR","id_candidatura":"72","incluir_en_calculo_porcentaje":true,"nombre_corto":"IEUP","nro_lista":"72"},{"candidatos_principales":{"CON":{"descripcion":"JOSU\u00c9 ALEXIS SEBASTIAN VAZQUEZ","dni":"35165519","id_candidatura":"901.2"},"INT":{"descripcion":"NORMA ESTHER SEPULVEDA","dni":"28002795","id_candidatura":"901.1"}},"clase":"Lista","color":null,"descripcion_lista":"JUNTOS","id_candidatura":"901","incluir_en_calculo_porcentaje":true,"nombre_corto":"JS","nro_lista":"901"},{"candidatos_principales":{"CON":{"descripcion":"MARIA ALEJANDRA LUQUI","dni":"16706981","id_candidatura":"915.121"},"INT":{"descripcion":"NORMA ESTHER SEPULVEDA","dni":"28002795","id_candidatura":"915.120"}},"clase":"Lista","color":null,"descripcion_lista":"PARTIDO VECINAL RENOVADOR","id_candidatura":"915","incluir_en_calculo_porcentaje":true,"nombre_corto":"PVR","nro_lista":"915"},{"candidatos_principales":{"CON":{"descripcion":"GUILLERMO AVALOS","dni":"29755937","id_candidatura":"921.47"},"INT":{"descripcion":"HECTOR ROBERTO BOLLANI","dni":"16955567","id_candidatura":"921.46"}},"clase":"Lista","color":null,"descripcion_lista":"INCLUSION Y TRABAJO","id_candidatura":"921","incluir_en_calculo_porcentaje":true,"nombre_corto":"IYT","nro_lista":"921"},{"clase":"Blanco","color":null,"descripcion_lista":"Voto en Blanco","id_candidatura":"BLC","incluir_en_calculo_porcentaje":true,"nombre_corto":"BLC","nro_lista":null},{"clase":"Especial","color":null,"descripcion_lista":"Votos Impugnados","id_candidatura":"IMP","incluir_en_calculo_porcentaje":false,"nombre_corto":"IMP","nro_lista":null},{"clase":"Especial","color":null,"descripcion_lista":"Total Observados","id_candidatura":"OBS","incluir_en_calculo_porcentaje":false,"nombre_corto":"TOT","nro_lista":null}],"cargos_habilitados":["INT","CON"],"clase_ubicacion":"Localidad","descripcion_ubicacion":"Rincon De Los Sauces","espejos":{"CON":[{"clase":"Espejo","descripcion":"Listas que llevan como candidato\/a a DANIEL ANGEL ARAVENA","id_candidatura":"151.32","id_espejo":"23346678","id_foto":"151.32","listas":[{"clase":"Lista","color":null,"descripcion_lista":"MOVIMIENTO POPULAR NEUQUINO","id_candidatura":"151","incluir_en_calculo_porcentaje":true,"nombre_corto":"MPN","nro_lista":"151"},{"clase":"Lista","color":null,"descripcion_lista":"UNION DE LOS NEUQUINOS - UNE","id_candidatura":"166","incluir_en_calculo_porcentaje":true,"nombre_corto":"UN","nro_lista":"166"}]},{"clase":"Espejo","descripcion":"Listas que llevan como candidato\/a a RICARDO GABRIEL MU\u00d1OZ","id_candidatura":"194.61","id_espejo":"16979944","id_foto":"194.61","listas":[{"clase":"Lista","color":null,"descripcion_lista":"ENCUENTRO REPUBLICANO FEDERAL","id_candidatura":"194","incluir_en_calculo_porcentaje":true,"nombre_corto":"ERF","nro_lista":"194"}]},{"clase":"Espejo","descripcion":"Listas que llevan como candidato\/a a LUCIANO JUAN DOMINGO JOUBERT","id_candidatura":"50.76","id_espejo":"29045889","id_foto":"50.76","listas":[{"clase":"Lista","color":null,"descripcion_lista":"PARTIDO SOCIALISTA","id_candidatura":"50","incluir_en_calculo_porcentaje":true,"nombre_corto":"PS","nro_lista":"50"}]},{"clase":"Espejo","descripcion":"Listas que llevan como candidato\/a a JUAN JOSE MALDONADO","id_candidatura":"67.91","id_espejo":"16831451","id_foto":"67.91","listas":[{"clase":"Lista","color":null,"descripcion_lista":"KOLINA","id_candidatura":"67","incluir_en_calculo_porcentaje":true,"nombre_corto":"KL","nro_lista":"67"}]},{"clase":"Espejo","descripcion":"Listas que llevan como candidato\/a a WALTER JOSE ZOZAYA","id_candidatura":"72.17","id_espejo":"22910330","id_foto":"72.17","listas":[{"clase":"Lista","color":null,"descripcion_lista":"INSTRUMENTO ELECTORAL POR LA UNIDAD POPULAR","id_candidatura":"72","incluir_en_calculo_porcentaje":true,"nombre_corto":"IEUP","nro_lista":"72"}]},{"clase":"Espejo","descripcion":"Listas que llevan como candidato\/a a JOSU\u00c9 ALEXIS SEBASTIAN VAZQUEZ","id_candidatura":"901.2","id_espejo":"35165519","id_foto":"901.2","listas":[{"clase":"Lista","color":null,"descripcion_lista":"JUNTOS","id_candidatura":"901","incluir_en_calculo_porcentaje":true,"nombre_corto":"JS","nro_lista":"901"}]},{"clase":"Espejo","descripcion":"Listas que llevan como candidato\/a a MARIA ALEJANDRA LUQUI","id_candidatura":"915.121","id_espejo":"16706981","id_foto":"915.121","listas":[{"clase":"Lista","color":null,"descripcion_lista":"PARTIDO VECINAL RENOVADOR","id_candidatura":"915","incluir_en_calculo_porcentaje":true,"nombre_corto":"PVR","nro_lista":"915"}]},{"clase":"Espejo","descripcion":"Listas que llevan como candidato\/a a GUILLERMO AVALOS","id_candidatura":"921.47","id_espejo":"29755937","id_foto":"921.47","listas":[{"clase":"Lista","color":null,"descripcion_lista":"INCLUSION Y TRABAJO","id_candidatura":"921","incluir_en_calculo_porcentaje":true,"nombre_corto":"IYT","nro_lista":"921"}]}],"INT":[{"clase":"Espejo","descripcion":"Listas que llevan como candidato\/a a NORMA ESTHER SEPULVEDA","id_candidatura":"151.31","id_espejo":"28002795","id_foto":"151.31","listas":[{"clase":"Lista","color":null,"descripcion_lista":"MOVIMIENTO POPULAR NEUQUINO","id_candidatura":"151","incluir_en_calculo_porcentaje":true,"nombre_corto":"MPN","nro_lista":"151"},{"clase":"Lista","color":null,"descripcion_lista":"UNION DE LOS NEUQUINOS - UNE","id_candidatura":"166","incluir_en_calculo_porcentaje":true,"nombre_corto":"UN","nro_lista":"166"},{"clase":"Lista","color":null,"descripcion_lista":"JUNTOS","id_candidatura":"901","incluir_en_calculo_porcentaje":true,"nombre_corto":"JS","nro_lista":"901"},{"clase":"Lista","color":null,"descripcion_lista":"PARTIDO VECINAL RENOVADOR","id_candidatura":"915","incluir_en_calculo_porcentaje":true,"nombre_corto":"PVR","nro_lista":"915"}]},{"clase":"Espejo","descripcion":"Listas que llevan como candidato\/a a JOSE ALBERTO QUINTERO MARCO","id_candidatura":"194.60","id_espejo":"22473462","id_foto":"194.60","listas":[{"clase":"Lista","color":null,"descripcion_lista":"ENCUENTRO REPUBLICANO FEDERAL","id_candidatura":"194","incluir_en_calculo_porcentaje":true,"nombre_corto":"ERF","nro_lista":"194"},{"clase":"Lista","color":null,"descripcion_lista":"PARTIDO SOCIALISTA","id_candidatura":"50","incluir_en_calculo_porcentaje":true,"nombre_corto":"PS","nro_lista":"50"}]},{"clase":"Espejo","descripcion":"Listas que llevan como candidato\/a a CESAR AURELIO GODOY","id_candidatura":"67.90","id_espejo":"31530215","id_foto":"67.90","listas":[{"clase":"Lista","color":null,"descripcion_lista":"KOLINA","id_candidatura":"67","incluir_en_calculo_porcentaje":true,"nombre_corto":"KL","nro_lista":"67"},{"clase":"Lista","color":null,"descripcion_lista":"INSTRUMENTO ELECTORAL POR LA UNIDAD POPULAR","id_candidatura":"72","incluir_en_calculo_porcentaje":true,"nombre_corto":"IEUP","nro_lista":"72"}]},{"clase":"Espejo","descripcion":"Listas que llevan como candidato\/a a HECTOR ROBERTO BOLLANI","id_candidatura":"921.46","id_espejo":"16955567","id_foto":"921.46","listas":[{"clase":"Lista","color":null,"descripcion_lista":"INCLUSION Y TRABAJO","id_candidatura":"921","incluir_en_calculo_porcentaje":true,"nombre_corto":"IYT","nro_lista":"921"}]}]},"id_ubicacion":"RS","mesas_habilitadas":56,"mesas_habilitadas_por_cargo":{"CON":56,"INT":56},"votantes_habilitados":19091,"votantes_habilitados_por_cargo":{"CON":19091,"INT":19091}}